pluggable_app_engine/__init__.py
pluggable_app_engine/app_context.py
pluggable_app_engine-0.2.dist-info/LICENSE
pluggable_app_engine-0.2.dist-info/METADATA
pluggable_app_engine-0.2.dist-info/WHEEL
pluggable_app_engine-0.2.dist-info/top_level.txt
pluggable_app_engine-0.2.dist-info/RECORD
