Metadata-Version: 2.1
Name: pluggable-app-engine
Version: 0.2
Summary: A small library for creating pluggable app
Home-page: https://github.com/mikolajtr/pluggable_app_engine
Author: Mikołaj Trawiński
Author-email: devnull@mikolajtrawinski.pl
License: UNKNOWN
Platform: UNKNOWN
Classifier: Programming Language :: Python :: 3
Classifier: License :: OSI Approved :: MIT License
Classifier: Operating System :: OS Independent
Requires-Python: >=3.5.3
License-File: LICENSE
